nuqui/__init__.py
nuqui/dbobjects.py
nuqui/nuqui.py
nuqui/data/nuqui.db
nuqui-0.1.6.dist-info/DESCRIPTION.rst
nuqui-0.1.6.dist-info/METADATA
nuqui-0.1.6.dist-info/RECORD
nuqui-0.1.6.dist-info/WHEEL
nuqui-0.1.6.dist-info/metadata.json
nuqui-0.1.6.dist-info/top_level.txt
