Metadata-Version: 2.0
Name: nuqui
Version: 0.1.6
Summary: A small quiz application
Home-page: UNKNOWN
Author: Tanja Kuery and Lars Voegtlin
Author-email: lars.voegtlin@unifr.ch
License: UNKNOWN
Platform: UNKNOWN
Classifier: Development Status :: 3 - Alpha
Classifier: Intended Audience :: Developers
Classifier: License :: OSI Approved :: GNU General Public License v3 (GPLv3)
Classifier: Programming Language :: Python :: 3.6
Requires-Dist: sqlalchemy
